{
  "work": "Prayers and Meditations",
  "slug": "prayers-and-meditations",
  "author": "Bahá'u'lláh",
  "pair_index": 252,
  "source_text": "وُجُوهُ أَهْلِ مَلأِ الأَعْلی، أَسْئَلُكَ يا مالِكَ الأَسْمآءِ بِأَنْ تَحْفَظَ أَحِبَّتَكَ مِنْ أَعْدائِكَ ثُمَّ أَثْبِتْهُمْ عَلَى حُبِّكَ وَرِضائِكَ فَاحْفَظْ أَرْجُلَهُمْ عَنِ الزَّلَلِ وَقُلُوبَهُمْ عَنِ الحُجُباتِ وَعُيُونَهُمْ عَنِ الإِغْضاءِ وَاجْتَذِبْهُمْ بِنَغَماتِ عِزِّ أَحَدِيَّتِكَ عَلَى شَأْنٍ يَنْقَطِعُنَّ عمَّا سِواكَ وَيُقْلَبُنَّ إِلَيكَ وَيَنْطِقُنَّ فِي كُلِّ الأَحْوالِ، لَكَ الحَمْدُ يا إِلهِي بِما عَرَّفْتَنا نَفْسَكَ العَلِيَّ الأَبْهی، نَحْنُ بِفَضْلِكَ نَكُونُ مُتَمَسِّكًا بِكَ وَمُنْقَطِعًا عَمَّا سِواكَ وَعَلِمْنا بِأَنَّكَ أَنْتَ مَحْبُوبُ العالَمِينَ وَفاطِرُ السَّمَواتِ وَالأَرَضِينَ وَالحَمْدُ",
  "translation": "I beseech Thee, O Thou Who art the Lord of all names, to guard Thy loved ones against Thine enemies, and to strengthen them in their love for Thee and in fulfilling Thy pleasure. Do Thou protect them, that their footsteps may slip not, that their hearts may not be shut out as by a veil from Thee, and that their eyes may be restrained from beholding anything that is not of Thee. Cause them to be so enraptured by the sweetness of Thy divine melodies that they will rid themselves of all attachment to any one except Thee, and will turn wholly towards Thee, and extol Thee under all conditions, saying: “Praised be Thou, O Lord our God, inasmuch as Thou hast enabled us to recognize Thy most exalted and all-glorious Self. We will, by Thy mercy, cleave to Thee, and will detach ourselves from any one but Thee. We have realized that Thou art the Beloved of the worlds and the Creator of earth and heaven!”",
  "source_lang": "ar",
  "score": 9.9,
  "page_slug": "guard-loved-ones-divine-melodies",
  "alignment": [
    {
      "ar": "أَهْلِ مَلأِ الأَعْلی،",
      "en": "the Lord of all names",
      "src": [
        8,
        30
      ],
      "tgt": [
        31,
        52
      ]
    },
    {
      "ar": "مِنْ أَعْدائِكَ",
      "en": "against Thine enemies",
      "src": [
        91,
        106
      ],
      "tgt": [
        78,
        99
      ]
    },
    {
      "ar": "عَلَى حُبِّكَ",
      "en": "in their love for Thee",
      "src": [
        126,
        139
      ],
      "tgt": [
        124,
        146
      ]
    },
    {
      "ar": "أَرْجُلَهُمْ عَنِ الزَّلَلِ",
      "en": "that their footsteps may slip not",
      "src": [
        161,
        188
      ],
      "tgt": [
        201,
        234
      ]
    },
    {
      "ar": "بِنَغَماتِ عِزِّ أَحَدِيَّتِكَ",
      "en": "by the sweetness of Thy divine melodies",
      "src": [
        265,
        295
      ],
      "tgt": [
        412,
        451
      ]
    },
    {
      "ar": "فِي كُلِّ الأَحْوالِ،",
      "en": "under all conditions",
      "src": [
        372,
        393
      ],
      "tgt": [
        574,
        594
      ]
    },
    {
      "ar": "يا إِلهِي",
      "en": "O Lord our God",
      "src": [
        408,
        417
      ],
      "tgt": [
        622,
        636
      ]
    },
    {
      "ar": "نَفْسَكَ العَلِيَّ الأَبْهی،",
      "en": "Thy most exalted and all-glorious Self",
      "src": [
        435,
        463
      ],
      "tgt": [
        684,
        722
      ]
    },
    {
      "ar": "مَحْبُوبُ العالَمِينَ",
      "en": "the Beloved of the worlds",
      "src": [
        564,
        585
      ],
      "tgt": [
        843,
        868
      ]
    },
    {
      "ar": "وَفاطِرُ السَّمَواتِ وَالأَرَضِينَ",
      "en": "the Creator of earth and heaven!”",
      "src": [
        586,
        620
      ],
      "tgt": [
        873,
        906
      ]
    },
    {
      "ar": "وُجُوهُ",
      "en": "ones",
      "src": [
        0,
        7
      ],
      "tgt": [
        73,
        77
      ]
    },
    {
      "ar": "أَسْئَلُكَ",
      "en": "I beseech",
      "src": [
        31,
        41
      ],
      "tgt": [
        0,
        9
      ]
    },
    {
      "ar": "يا",
      "en": "O",
      "src": [
        42,
        44
      ],
      "tgt": [
        16,
        17
      ]
    },
    {
      "ar": "مالِكَ",
      "en": "Who art",
      "src": [
        45,
        51
      ],
      "tgt": [
        23,
        30
      ]
    },
    {
      "ar": "بِأَنْ",
      "en": "to",
      "src": [
        63,
        69
      ],
      "tgt": [
        54,
        56
      ]
    },
    {
      "ar": "تَحْفَظَ",
      "en": "guard",
      "src": [
        70,
        78
      ],
      "tgt": [
        57,
        62
      ]
    },
    {
      "ar": "ثُمَّ",
      "en": "and",
      "src": [
        107,
        112
      ],
      "tgt": [
        101,
        104
      ]
    },
    {
      "ar": "أَثْبِتْهُمْ",
      "en": "strengthen",
      "src": [
        113,
        125
      ],
      "tgt": [
        108,
        118
      ]
    },
    {
      "ar": "وَرِضائِكَ",
      "en": "Thy pleasure",
      "src": [
        140,
        150
      ],
      "tgt": [
        165,
        177
      ]
    },
    {
      "ar": "فَاحْفَظْ",
      "en": "Do Thou protect",
      "src": [
        151,
        160
      ],
      "tgt": [
        179,
        194
      ]
    },
    {
      "ar": "وَقُلُوبَهُمْ",
      "en": "their hearts",
      "src": [
        189,
        202
      ],
      "tgt": [
        241,
        253
      ]
    },
    {
      "ar": "عَنِ",
      "en": "from",
      "src": [
        203,
        207
      ],
      "tgt": [
        287,
        291
      ]
    },
    {
      "ar": "الحُجُباتِ",
      "en": "a veil",
      "src": [
        208,
        218
      ],
      "tgt": [
        280,
        286
      ]
    },
    {
      "ar": "وَعُيُونَهُمْ",
      "en": "their eyes",
      "src": [
        219,
        232
      ],
      "tgt": [
        307,
        317
      ]
    },
    {
      "ar": "الإِغْضاءِ",
      "en": "beholding",
      "src": [
        238,
        248
      ],
      "tgt": [
        341,
        350
      ]
    },
    {
      "ar": "وَاجْتَذِبْهُمْ",
      "en": "Cause them",
      "src": [
        249,
        264
      ],
      "tgt": [
        381,
        391
      ]
    },
    {
      "ar": "عَلَى",
      "en": "towards",
      "src": [
        296,
        301
      ],
      "tgt": [
        545,
        552
      ]
    },
    {
      "ar": "شَأْنٍ",
      "en": "so",
      "src": [
        302,
        308
      ],
      "tgt": [
        398,
        400
      ]
    },
    {
      "ar": "يَنْقَطِعُنَّ",
      "en": "will rid",
      "src": [
        309,
        322
      ],
      "tgt": [
        462,
        470
      ]
    },
    {
      "ar": "عمَّا",
      "en": "except",
      "src": [
        323,
        328
      ],
      "tgt": [
        511,
        517
      ]
    },
    {
      "ar": "سِواكَ",
      "en": "Thee",
      "src": [
        329,
        335
      ],
      "tgt": [
        518,
        522
      ]
    },
    {
      "ar": "وَيُقْلَبُنَّ",
      "en": "will turn",
      "src": [
        336,
        349
      ],
      "tgt": [
        528,
        537
      ]
    },
    {
      "ar": "وَيَنْطِقُنَّ",
      "en": "extol",
      "src": [
        358,
        371
      ],
      "tgt": [
        563,
        568
      ]
    },
    {
      "ar": "لَكَ",
      "en": "“Praised",
      "src": [
        394,
        398
      ],
      "tgt": [
        604,
        612
      ]
    },
    {
      "ar": "الحَمْدُ",
      "en": "be",
      "src": [
        399,
        407
      ],
      "tgt": [
        613,
        615
      ]
    },
    {
      "ar": "بِما",
      "en": "inasmuch as",
      "src": [
        418,
        422
      ],
      "tgt": [
        638,
        649
      ]
    },
    {
      "ar": "عَرَّفْتَنا",
      "en": "hast enabled us to recognize",
      "src": [
        423,
        434
      ],
      "tgt": [
        655,
        683
      ]
    },
    {
      "ar": "نَحْنُ",
      "en": "We",
      "src": [
        464,
        470
      ],
      "tgt": [
        724,
        726
      ]
    },
    {
      "ar": "بِفَضْلِكَ",
      "en": "by Thy mercy",
      "src": [
        471,
        481
      ],
      "tgt": [
        733,
        745
      ]
    },
    {
      "ar": "نَكُونُ",
      "en": "will",
      "src": [
        482,
        489
      ],
      "tgt": [
        727,
        731
      ]
    },
    {
      "ar": "مُتَمَسِّكًا",
      "en": "cleave",
      "src": [
        490,
        502
      ],
      "tgt": [
        747,
        753
      ]
    },
    {
      "ar": "بِكَ",
      "en": "to Thee",
      "src": [
        503,
        507
      ],
      "tgt": [
        754,
        761
      ]
    },
    {
      "ar": "وَمُنْقَطِعًا",
      "en": "will detach",
      "src": [
        508,
        521
      ],
      "tgt": [
        767,
        778
      ]
    },
    {
      "ar": "عَمَّا",
      "en": "but",
      "src": [
        522,
        528
      ],
      "tgt": [
        802,
        805
      ]
    },
    {
      "ar": "وَعَلِمْنا",
      "en": "We have realized",
      "src": [
        536,
        546
      ],
      "tgt": [
        812,
        828
      ]
    },
    {
      "ar": "بِأَنَّكَ",
      "en": "that",
      "src": [
        547,
        556
      ],
      "tgt": [
        829,
        833
      ]
    },
    {
      "ar": "أَنْتَ",
      "en": "Thou art",
      "src": [
        557,
        563
      ],
      "tgt": [
        834,
        842
      ]
    }
  ],
  "terms": [
    {
      "term": "الحُجُباتِ",
      "transliteration": "ḥ-j-j",
      "literal": "path, way; clear path",
      "se_rendering": "veil",
      "note": "Root ḥ-j-j renders as 'Sanctuary,' 'Proofs,' or 'veils' across the corpus. SE renders 'veil' here, signifying spiritual separation from God — a cardinal Bahá'í concept.",
      "cross_refs": [
        {
          "work": "will-and-testament",
          "para": 1,
          "snippet": "Sanctuary"
        },
        {
          "work": "will-and-testament",
          "para": 2,
          "snippet": "with proofs"
        },
        {
          "work": "will-and-testament",
          "para": 45,
          "snippet": "Proofs"
        },
        {
          "work": "tablet-of-ahmad",
          "para": 7,
          "snippet": "proof"
        },
        {
          "work": "kitab-i-iqan",
          "para": 262,
          "snippet": "testimony"
        },
        {
          "work": "kitab-i-iqan",
          "para": 231,
          "snippet": "argument"
        }
      ]
    },
    {
      "term": "بِنَغَماتِ",
      "transliteration": "n-gh-m",
      "literal": "melody; tone; note",
      "se_rendering": "melodies",
      "note": "Root n-gh-m has only 10 occurrences; consistently 'melodies' or 'strain.' SE uses 'sweetness of Thy divine melodies,' creating a sensory, mystical image unique in phrasing.",
      "cross_refs": [
        {
          "work": "epistle-to-the-son-of-the-wolf",
          "para": 207,
          "snippet": "melodies"
        },
        {
          "work": "kitab-i-iqan",
          "para": 141,
          "snippet": "strain"
        },
        {
          "work": "kitab-i-iqan",
          "para": 179,
          "snippet": "melody"
        }
      ]
    },
    {
      "term": "أَحَدِيَّتِكَ",
      "transliteration": "h-d-y",
      "literal": "oneness; unity; absolute unicity; singleness of divine essence",
      "se_rendering": "divine melodies",
      "note": "Root ḥ-d-y indicates 'oneness' or 'unity.' SE integrates this into 'sweetness of Thy divine melodies' — an unusual fusion with the preceding term, not isolated as a separate concept.",
      "cross_refs": [
        {
          "work": "kitab-i-iqan",
          "para": 216,
          "snippet": "the Divine Oneness"
        }
      ]
    },
    {
      "term": "الأَبْهی",
      "transliteration": "b-h-y",
      "literal": "splendor; glory; magnificence; Bahá (Proper Name in Bahá'í texts)",
      "se_rendering": "all-glorious",
      "note": "Root b-h-y renders as 'Bahá,' 'Glory,' or 'All-Glorious.' SE uses 'all-glorious' here within 'exalted and all-glorious Self,' reserving proper-noun 'Bahá' for other contexts.",
      "cross_refs": [
        {
          "work": "gleanings",
          "para": 89,
          "snippet": "Bahá"
        },
        {
          "work": "will-and-testament",
          "para": 59,
          "snippet": "Glory"
        },
        {
          "work": "epistle-to-the-son-of-the-wolf",
          "para": 51,
          "snippet": "Abhá"
        },
        {
          "work": "gleanings",
          "para": 645,
          "snippet": "All-Glorious"
        }
      ]
    },
    {
      "term": "وفاطِرُ",
      "transliteration": "f-ṭ-r",
      "literal": "creator; the one who splits/creates",
      "se_rendering": "Creator",
      "note": "Root f-ṭ-r typically 'Creator' or 'Maker.' SE uses 'Creator' here, maintaining standard cosmic nomenclature in the closing doxology acknowledging divine creation of heaven and earth.",
      "cross_refs": [
        {
          "work": "gleanings",
          "para": 47,
          "snippet": "Creator"
        },
        {
          "work": "epistle-to-the-son-of-the-wolf",
          "para": 138,
          "snippet": "the true Faith"
        },
        {
          "work": "gleanings",
          "para": 300,
          "snippet": "the nature made by God"
        },
        {
          "work": "epistle-to-the-son-of-the-wolf",
          "para": 236,
          "snippet": "inner ears"
        },
        {
          "work": "kitab-i-iqan",
          "para": 27,
          "snippet": "hearts"
        },
        {
          "work": "gleanings",
          "para": 117,
          "snippet": "Essence"
        },
        {
          "work": "gleanings",
          "para": 41,
          "snippet": "nature"
        },
        {
          "work": "kitab-i-iqan",
          "para": 46,
          "snippet": "cleaving of the heaven"
        }
      ]
    }
  ],
  "section_index": "LXI.3",
  "section": "LXI",
  "section_para": 3
}
