{
  "work": "Prayers and Meditations",
  "slug": "prayers-and-meditations",
  "author": "Bahá'u'lláh",
  "pair_index": 602,
  "source_text": "أَوَّلِيَّتِكَ وَظَاهِرِيَّتِكَ الَّتِيْ كانَتْ عَيْنَ باطِنِيَّتِكَ بِأَنْ تَجْعَلَ أَحِبَّائَكَ وَأَبْنائَهُمْ وَذَوِيْ قَرابَتِهِمْ مَظاهِرَ تَقْدِيْسِكَ بَيْنَ خَلْقِكَ وَمَطالِعَ تَنْزِيهِكَ بَيْنَ عِبادِكَ إِنَّكَ أَنْتَ",
  "translation": "I beseech Thee by Thy Lastness which is the same as Thy Firstness, and by Thy Revelation which is identical with Thy Concealment, to grant that they who are dear to Thee, and their children, and their kindred, may become the revealers of Thy purity amidst Thy creatures, and the manifestations of Thy sanctity amongst Thy servants.",
  "source_lang": "ar",
  "score": 10,
  "page_slug": "revealers-of-purity-sanctity",
  "alignment": [
    {
      "ar": "عَيْنَ باطِنِيَّتِكَ",
      "en": "Thy Concealment",
      "src": [
        48,
        68
      ],
      "tgt": [
        113,
        128
      ]
    },
    {
      "ar": "وَذَوِيْ قَرابَتِهِمْ",
      "en": "their kindred",
      "src": [
        113,
        134
      ],
      "tgt": [
        195,
        208
      ]
    },
    {
      "ar": "مَظاهِرَ تَقْدِيْسِكَ",
      "en": "revealers of Thy purity",
      "src": [
        135,
        156
      ],
      "tgt": [
        225,
        248
      ]
    },
    {
      "ar": "بَيْنَ خَلْقِكَ",
      "en": "amidst Thy creatures",
      "src": [
        157,
        172
      ],
      "tgt": [
        249,
        269
      ]
    },
    {
      "ar": "وَمَطالِعَ تَنْزِيهِكَ",
      "en": "manifestations of Thy sanctity",
      "src": [
        173,
        195
      ],
      "tgt": [
        279,
        309
      ]
    },
    {
      "ar": "بَيْنَ عِبادِكَ",
      "en": "amongst Thy servants",
      "src": [
        196,
        211
      ],
      "tgt": [
        310,
        330
      ]
    },
    {
      "ar": "أَوَّلِيَّتِكَ",
      "en": "Firstness",
      "src": [
        0,
        14
      ],
      "tgt": [
        56,
        65
      ]
    },
    {
      "ar": "وَظَاهِرِيَّتِكَ",
      "en": "Revelation",
      "src": [
        15,
        31
      ],
      "tgt": [
        78,
        88
      ]
    },
    {
      "ar": "الَّتِيْ",
      "en": "which",
      "src": [
        32,
        40
      ],
      "tgt": [
        31,
        36
      ]
    },
    {
      "ar": "كانَتْ",
      "en": "is",
      "src": [
        41,
        47
      ],
      "tgt": [
        37,
        39
      ]
    },
    {
      "ar": "بِأَنْ",
      "en": "to",
      "src": [
        69,
        75
      ],
      "tgt": [
        130,
        132
      ]
    },
    {
      "ar": "تَجْعَلَ",
      "en": "grant",
      "src": [
        76,
        84
      ],
      "tgt": [
        133,
        138
      ]
    },
    {
      "ar": "أَحِبَّائَكَ",
      "en": "they who are dear to Thee",
      "src": [
        85,
        97
      ],
      "tgt": [
        144,
        169
      ]
    },
    {
      "ar": "وَأَبْنائَهُمْ",
      "en": "their children",
      "src": [
        98,
        112
      ],
      "tgt": [
        175,
        189
      ]
    },
    {
      "ar": "إِنَّكَ",
      "en": "may",
      "src": [
        212,
        219
      ],
      "tgt": [
        210,
        213
      ]
    },
    {
      "ar": "أَنْتَ",
      "en": "become",
      "src": [
        220,
        226
      ],
      "tgt": [
        214,
        220
      ]
    }
  ],
  "terms": [
    {
      "term": "باطِنِيَّتِكَ",
      "transliteration": "b-ṭ-n",
      "literal": "inner; hidden; inward; esoteric",
      "se_rendering": "Concealment",
      "note": "Usually 'concealment' or 'inner life' (13 occurrences). Capitalization of 'Concealment' here marks it as parallel theological principle to Firstness/Lastness paradox.",
      "cross_refs": [
        {
          "work": "epistle-to-the-son-of-the-wolf",
          "para": 23,
          "snippet": "inwardly"
        },
        {
          "work": "gleanings",
          "para": 362,
          "snippet": "inner life"
        },
        {
          "work": "kitab-i-iqan",
          "para": 132,
          "snippet": "spiritual"
        },
        {
          "work": "gleanings",
          "para": 405,
          "snippet": "smirched and mired"
        },
        {
          "work": "gleanings",
          "para": 493,
          "snippet": "be"
        },
        {
          "work": "gleanings",
          "para": 248,
          "snippet": "wombs"
        },
        {
          "work": "gleanings",
          "para": 521,
          "snippet": "bosom"
        }
      ]
    },
    {
      "term": "أَحِبَّائَكَ",
      "transliteration": "ḥ-b-b",
      "literal": "love; affection",
      "se_rendering": "they who are dear to Thee",
      "note": "Typically 'beloved of the Lord' or 'loved ones' (92 occurrences). Circuitous relative clause 'they who are dear to Thee' distances the rendering from standard nominal form.",
      "cross_refs": [
        {
          "work": "will-and-testament",
          "para": 3,
          "snippet": "beloved of the Lord"
        },
        {
          "work": "will-and-testament",
          "para": 53,
          "snippet": "loved ones of the Lord"
        },
        {
          "work": "gleanings",
          "para": 341,
          "snippet": "loved ones of God"
        },
        {
          "work": "gleanings",
          "para": 689,
          "snippet": "beloved of the one true God"
        },
        {
          "work": "gleanings",
          "para": 640,
          "snippet": "loved ones"
        },
        {
          "work": "gleanings",
          "para": 690,
          "snippet": "beloved of God"
        },
        {
          "work": "epistle-to-the-son-of-the-wolf",
          "para": 39,
          "snippet": "His loved ones"
        },
        {
          "work": "will-and-testament",
          "para": 10,
          "snippet": "love for Thee"
        }
      ]
    },
    {
      "term": "مَظاهِرَ",
      "transliteration": "z-h-r",
      "literal": "manifestation; appearance; to appear; to manifest",
      "se_rendering": "revealers",
      "note": "Usually 'Manifestation' (96 occurrences in corpus). Here rendered 'revealers' — verbal participle form emphasizing active revelation rather than static manifestation.",
      "cross_refs": [
        {
          "work": "gleanings",
          "para": 53,
          "snippet": "Manifestation"
        },
        {
          "work": "kitab-i-iqan",
          "para": 136,
          "snippet": "evident"
        },
        {
          "work": "gleanings",
          "para": 222,
          "snippet": "material"
        },
        {
          "work": "kitab-i-ahd",
          "para": 11,
          "snippet": "revealed"
        },
        {
          "work": "epistle-to-the-son-of-the-wolf",
          "para": 206,
          "snippet": "appeared"
        },
        {
          "work": "kitab-i-ahd",
          "para": 8,
          "snippet": "daysprings of authority and sources of command"
        },
        {
          "work": "kitab-i-iqan",
          "para": 196,
          "snippet": "Manifestations of God"
        },
        {
          "work": "will-and-testament",
          "para": 32,
          "snippet": "overwhelm the soul"
        }
      ]
    },
    {
      "term": "تَقْدِيْسِكَ",
      "transliteration": "q-d-s",
      "literal": "holy, sacred, sanctified",
      "se_rendering": "purity",
      "note": "Typically 'Sacred' or 'hallowed' (47 occurrences). SE chooses 'purity' here, importing abstract quality over the root's primary sanctification sense.",
      "cross_refs": [
        {
          "work": "will-and-testament",
          "para": 2,
          "snippet": "Sacred"
        },
        {
          "work": "epistle-to-the-son-of-the-wolf",
          "para": 81,
          "snippet": "hallowed"
        },
        {
          "work": "the-hidden-words",
          "para": 35,
          "snippet": "spirit of holiness"
        },
        {
          "work": "gleanings",
          "para": 585,
          "snippet": "holy Paradise"
        },
        {
          "work": "tablet-of-the-holy-mariner",
          "para": 13,
          "snippet": "Holy Mariner"
        },
        {
          "work": "gleanings",
          "para": 584,
          "snippet": "Holy Veil"
        },
        {
          "work": "tablet-of-the-holy-mariner",
          "para": 6,
          "snippet": "sacred strand"
        },
        {
          "work": "tablet-of-the-holy-mariner",
          "para": 26,
          "snippet": "Celestial Concourse"
        }
      ]
    },
    {
      "term": "خَلْقِكَ",
      "transliteration": "kh-l-q",
      "literal": "character; moral traits; disposition; conduct",
      "se_rendering": "creatures",
      "note": "Root means 'character; moral traits' (49 occurrences), yet SE renders 'creatures' — shifting from abstract disposition to concrete beings, a rare semantic extension.",
      "cross_refs": [
        {
          "work": "epistle-to-the-son-of-the-wolf",
          "para": 28,
          "snippet": "character"
        },
        {
          "work": "epistle-to-the-son-of-the-wolf",
          "para": 50,
          "snippet": "spiritual characteristics"
        },
        {
          "work": "epistle-to-the-son-of-the-wolf",
          "para": 195,
          "snippet": "virtues"
        },
        {
          "work": "tablet-of-the-holy-mariner",
          "para": 54,
          "snippet": "created her"
        },
        {
          "work": "gleanings",
          "para": 451,
          "snippet": "His Apostle"
        },
        {
          "work": "epistle-to-the-son-of-the-wolf",
          "para": 2,
          "snippet": "His creation"
        },
        {
          "work": "fire-tablet",
          "para": 40,
          "snippet": "wert created"
        },
        {
          "work": "the-hidden-words",
          "para": 23,
          "snippet": "created thee"
        }
      ]
    },
    {
      "term": "تَنْزِيهِكَ",
      "transliteration": "n-z-h",
      "literal": "exalted; sanctified; free from; removed from",
      "se_rendering": "sanctity",
      "note": "Scarcest term in corpus (4 occurrences). SE chooses 'sanctity' over typical 'exalted' or 'purged,' emphasizing transcendent holiness alongside practical abstraction from defect.",
      "cross_refs": [
        {
          "work": "will-and-testament",
          "para": 15,
          "snippet": "purged"
        },
        {
          "work": "gleanings",
          "para": 182,
          "snippet": "sanctified"
        },
        {
          "work": "gleanings",
          "para": 496,
          "snippet": "sanctified and detached"
        }
      ]
    }
  ],
  "section_index": "CXL.2",
  "section": "CXL",
  "section_para": 2
}
