{
  "work": "Epistle to the Son of the Wolf",
  "slug": "epistle-to-the-son-of-the-wolf",
  "author": "Bahá'u'lláh",
  "pair_index": 122,
  "source_text": "در مازندران جمع کثيری از عباد اللّه را تمام نمودند حاکم بمفتريات جمعی را تاراج کرد * از جمله ذکر نمود حضرات اسلحه جمع کرده‌اند و بعد از تفحّص ملاحظه شد يک لوله تفنگ من غير اسباب بوده * سبحان اللّه اين حزب بسلاح محتاج نه چه که کمر همّت لاجل اصلاح عالم بسته‌اند * جندشان اعمال طيّبه سلاحشان اخلاق مرضيّه و سردارشان تقوی اللّه * طوبی لمن انصف * لعمر اللّه اين حزب از صبر و سکون و تسليم و رضا مظاهر عدل شده‌اند و در اصطبار بمقامی رسيده‌اند که کشته شده‌اند و نکشته‌اند مع انکه بر مظلومهای ارض وارد شد انچه که تاريخ عالم شبه ان را ذکر ننموده و چشم امم مثلش را نديده * ايا سبب انکه اين بلايای عظيمه را قبول نموده‌اند و در دفع ان دست در نياورده‌اند چه بوده و علّت تسليم و سکون چه ؟ سبب منع قلم اعلی در صباح و مساء و اخذ زمام امور بقدرت و قوّت مولی الوری *",
  "translation": "In Mázindarán a vast number of the servants of God were exterminated. The Governor, under the influence of calumniators, robbed a great many of all that they possessed. Among the charges he laid against them was that they had been laying up arms, whereas upon investigation it was found out that they had nothing but an unloaded rifle! Gracious God! This people need no weapons of destruction, inasmuch as they have girded themselves to reconstruct the world. Their hosts are the hosts of goodly deeds, and their arms the arms of upright conduct, and their commander the fear of God. Blessed that one that judgeth with fairness. By the righteousness of God! Such hath been the patience, the calm, the resignation and contentment of this people that they have become the exponents of justice, and so great hath been their forbearance, that they have suffered themselves to be killed rather than kill, and this notwithstanding that these whom the world hath wronged have endured tribulations the like of which the history of the world hath never recorded, nor the eyes of any nation witnessed. What is it that could have induced them to reconcile themselves to these grievous trials, and to refuse to put forth a hand to repel them? What could have caused such resignation and serenity? The true cause is to be found in the ban which the Pen of Glory hath, day and night, chosen to impose, and in Our assumption of the reins of authority, through the power and might of Him Who is the Lord of all mankind.",
  "source_lang": "fa",
  "score": 10,
  "page_slug": "patience-exponents-justice",
  "alignment": [
    {
      "ar": "مازندران",
      "en": "Mázindarán"
    },
    {
      "ar": "جمع",
      "en": "number"
    },
    {
      "ar": "کثيری",
      "en": "vast"
    },
    {
      "ar": "عباد",
      "en": "servants"
    },
    {
      "ar": "اللّه",
      "en": "God"
    },
    {
      "ar": "تمام",
      "en": "exterminated"
    },
    {
      "ar": "نمودند",
      "en": "were"
    },
    {
      "ar": "حاکم",
      "en": "Governor"
    },
    {
      "ar": "بمفتريات",
      "en": "calumniators"
    },
    {
      "ar": "جمعی",
      "en": "great many"
    },
    {
      "ar": "تاراج",
      "en": "robbed"
    },
    {
      "ar": "جمله",
      "en": "charges"
    },
    {
      "ar": "ذکر",
      "en": "laid"
    },
    {
      "ar": "حضرات",
      "en": "they"
    },
    {
      "ar": "اسلحه",
      "en": "arms"
    },
    {
      "ar": "جمع",
      "en": "laying up"
    },
    {
      "ar": "کرده‌اند",
      "en": "had been laying"
    },
    {
      "ar": "بعد",
      "en": "upon"
    },
    {
      "ar": "تفحّص",
      "en": "investigation"
    },
    {
      "ar": "ملاحظه",
      "en": "found out"
    },
    {
      "ar": "شد",
      "en": "was"
    },
    {
      "ar": "يک",
      "en": "nothing but"
    },
    {
      "ar": "لوله",
      "en": "rifle"
    },
    {
      "ar": "من",
      "en": "unloaded"
    },
    {
      "ar": "بوده",
      "en": "had"
    },
    {
      "ar": "سبحان",
      "en": "Gracious"
    },
    {
      "ar": "اين",
      "en": "This"
    },
    {
      "ar": "حزب",
      "en": "people"
    },
    {
      "ar": "بسلاح",
      "en": "weapons"
    },
    {
      "ar": "محتاج",
      "en": "need"
    },
    {
      "ar": "نه",
      "en": "no"
    },
    {
      "ar": "که",
      "en": "inasmuch"
    },
    {
      "ar": "کمر",
      "en": "girded"
    },
    {
      "ar": "لاجل",
      "en": "to"
    },
    {
      "ar": "اصلاح",
      "en": "reconstruct"
    },
    {
      "ar": "عالم",
      "en": "world"
    },
    {
      "ar": "بسته‌اند",
      "en": "have girded themselves"
    },
    {
      "ar": "جندشان",
      "en": "Their hosts"
    },
    {
      "ar": "اعمال",
      "en": "deeds"
    },
    {
      "ar": "طيّبه",
      "en": "goodly"
    },
    {
      "ar": "سلاحشان",
      "en": "their arms"
    },
    {
      "ar": "اخلاق",
      "en": "conduct"
    },
    {
      "ar": "مرضيّه",
      "en": "upright"
    },
    {
      "ar": "سردارشان",
      "en": "their commander"
    },
    {
      "ar": "تقوی",
      "en": "fear"
    },
    {
      "ar": "طوبی",
      "en": "Blessed"
    },
    {
      "ar": "لمن",
      "en": "that one that"
    },
    {
      "ar": "انصف",
      "en": "judgeth with fairness"
    },
    {
      "ar": "لعمر",
      "en": "By the righteousness"
    },
    {
      "ar": "اين",
      "en": "this"
    },
    {
      "ar": "صبر",
      "en": "patience"
    },
    {
      "ar": "سکون",
      "en": "calm"
    },
    {
      "ar": "تسليم",
      "en": "resignation"
    },
    {
      "ar": "رضا",
      "en": "contentment"
    },
    {
      "ar": "مظاهر",
      "en": "exponents"
    },
    {
      "ar": "عدل",
      "en": "justice"
    },
    {
      "ar": "شده‌اند",
      "en": "have become"
    },
    {
      "ar": "اصطبار",
      "en": "forbearance"
    },
    {
      "ar": "بمقامی",
      "en": "great"
    },
    {
      "ar": "رسيده‌اند",
      "en": "hath been"
    },
    {
      "ar": "کشته",
      "en": "killed"
    },
    {
      "ar": "شده‌اند",
      "en": "suffered themselves"
    },
    {
      "ar": "نکشته‌اند",
      "en": "rather than kill"
    },
    {
      "ar": "مع",
      "en": "notwithstanding"
    },
    {
      "ar": "انکه",
      "en": "that"
    },
    {
      "ar": "مظلومهای",
      "en": "wronged"
    },
    {
      "ar": "وارد",
      "en": "endured"
    },
    {
      "ar": "شد",
      "en": "have"
    },
    {
      "ar": "انچه",
      "en": "tribulations"
    },
    {
      "ar": "تاريخ",
      "en": "history"
    },
    {
      "ar": "شبه",
      "en": "like"
    },
    {
      "ar": "ان",
      "en": "which"
    },
    {
      "ar": "ذکر",
      "en": "recorded"
    },
    {
      "ar": "ننموده",
      "en": "never"
    },
    {
      "ar": "چشم",
      "en": "eyes"
    },
    {
      "ar": "امم",
      "en": "nation"
    },
    {
      "ar": "مثلش",
      "en": "witnessed"
    },
    {
      "ar": "ايا",
      "en": "What"
    },
    {
      "ar": "سبب",
      "en": "cause"
    },
    {
      "ar": "بلايای",
      "en": "trials"
    },
    {
      "ar": "عظيمه",
      "en": "grievous"
    },
    {
      "ar": "قبول",
      "en": "reconcile"
    },
    {
      "ar": "نموده‌اند",
      "en": "induced"
    },
    {
      "ar": "دفع",
      "en": "repel"
    },
    {
      "ar": "ان",
      "en": "them"
    },
    {
      "ar": "دست",
      "en": "hand"
    },
    {
      "ar": "در",
      "en": "put forth"
    },
    {
      "ar": "نياورده‌اند",
      "en": "refuse"
    },
    {
      "ar": "بوده",
      "en": "been"
    },
    {
      "ar": "علّت",
      "en": "caused"
    },
    {
      "ar": "سکون",
      "en": "serenity"
    },
    {
      "ar": "منع",
      "en": "ban"
    },
    {
      "ar": "قلم",
      "en": "Pen"
    },
    {
      "ar": "اعلی",
      "en": "Glory"
    },
    {
      "ar": "صباح",
      "en": "day"
    },
    {
      "ar": "مساء",
      "en": "night"
    },
    {
      "ar": "اخذ",
      "en": "assumption"
    },
    {
      "ar": "زمام",
      "en": "reins"
    },
    {
      "ar": "امور",
      "en": "authority"
    },
    {
      "ar": "بقدرت",
      "en": "power"
    },
    {
      "ar": "قوّت",
      "en": "might"
    },
    {
      "ar": "مولی",
      "en": "Lord"
    },
    {
      "ar": "الوری",
      "en": "mankind"
    }
  ],
  "terms": [
    {
      "term": "اخلاق",
      "transliteration": "kh-l-q",
      "literal": "character; moral traits; disposition; conduct",
      "se_rendering": "upright conduct",
      "note": "Patterns 'character' or 'virtues' (49 occ). 'Upright conduct' stresses behavioral ethics as weapon-substitute—practical morality over abstract disposition.",
      "cross_refs": [
        {
          "work": "will-and-testament",
          "para": 21,
          "snippet": "character"
        },
        {
          "work": "tablet-of-the-holy-mariner",
          "para": 54,
          "snippet": "created her"
        },
        {
          "work": "gleanings",
          "para": 451,
          "snippet": "His Apostle"
        },
        {
          "work": "prayers-and-meditations",
          "para": 231,
          "snippet": "His creatures"
        },
        {
          "work": "prayers-and-meditations",
          "para": 139,
          "snippet": "His creation"
        },
        {
          "work": "prayers-and-meditations",
          "para": 343,
          "snippet": "Thy creatures"
        },
        {
          "work": "fire-tablet",
          "para": 40,
          "snippet": "wert created"
        },
        {
          "work": "the-hidden-words",
          "para": 23,
          "snippet": "created thee"
        }
      ]
    },
    {
      "term": "صبر",
      "transliteration": "s-b-r",
      "literal": "patience; forbearance; endurance; to be patient",
      "se_rendering": "patience",
      "note": "Typically 'patience' or 'forbearance' (32 occ). Rendered as 'patience' here, introducing cardinal virtue that frames entire theodicy.",
      "cross_refs": [
        {
          "work": "will-and-testament",
          "para": 48,
          "snippet": "forbearance"
        },
        {
          "work": "fire-tablet",
          "para": 40,
          "snippet": "Patience of the worlds"
        },
        {
          "work": "the-hidden-words",
          "para": 49,
          "snippet": "patience"
        },
        {
          "work": "fire-tablet",
          "para": 39,
          "snippet": "Thy patience"
        },
        {
          "work": "kitab-i-iqan",
          "para": 251,
          "snippet": "their steadfastness"
        },
        {
          "work": "gleanings",
          "para": 620,
          "snippet": "be patient"
        },
        {
          "work": "gleanings",
          "para": 408,
          "snippet": "steadfast"
        },
        {
          "work": "prayers-and-meditations",
          "para": 689,
          "snippet": "patient"
        }
      ]
    },
    {
      "term": "مظاهر",
      "transliteration": "z-h-r",
      "literal": "manifestation; appearance; to appear; to manifest",
      "se_rendering": "exponents",
      "note": "Usually 'Manifestation' (deity-referential, 96 occ). Here 'exponents' denotes human carriers of divine justice—concrete embodiment rather than theophanic appearance.",
      "cross_refs": [
        {
          "work": "gleanings",
          "para": 53,
          "snippet": "Manifestation"
        },
        {
          "work": "prayers-and-meditations",
          "para": 160,
          "snippet": "Author of all Manifestations"
        },
        {
          "work": "kitab-i-iqan",
          "para": 136,
          "snippet": "evident"
        },
        {
          "work": "gleanings",
          "para": 222,
          "snippet": "material"
        },
        {
          "work": "kitab-i-ahd",
          "para": 11,
          "snippet": "revealed"
        },
        {
          "work": "kitab-i-ahd",
          "para": 8,
          "snippet": "daysprings of authority and sources of command"
        },
        {
          "work": "kitab-i-iqan",
          "para": 196,
          "snippet": "Manifestations of God"
        },
        {
          "work": "prayers-and-meditations",
          "para": 255,
          "snippet": "Manifestations"
        }
      ]
    },
    {
      "term": "عدل",
      "transliteration": "ʿ-d-l",
      "literal": "justice; equity",
      "se_rendering": "justice",
      "note": "Consistently 'justice' or 'equity' (29 occ). Rendered as 'justice' here; Bahá'í community becomes living manifestation of divine equity.",
      "cross_refs": [
        {
          "work": "will-and-testament",
          "para": 25,
          "snippet": "Justice"
        },
        {
          "work": "will-and-testament",
          "para": 8,
          "snippet": "just"
        },
        {
          "work": "prayers-and-meditations",
          "para": 145,
          "snippet": "Who dealest equitably"
        },
        {
          "work": "gleanings",
          "para": 21,
          "snippet": "with justice and equity"
        },
        {
          "work": "gleanings",
          "para": 538,
          "snippet": "as numerous as"
        },
        {
          "work": "the-hidden-words",
          "para": 79,
          "snippet": "disputeth"
        },
        {
          "work": "will-and-testament",
          "para": 24,
          "snippet": "Consort"
        },
        {
          "work": "gleanings",
          "para": 189,
          "snippet": "the Just"
        }
      ]
    },
    {
      "term": "بلایای",
      "transliteration": "b-l-ʾ",
      "literal": "affliction; trial; calamity",
      "se_rendering": "tribulations",
      "note": "Range from 'trials' to 'afflictions' (27 occ). 'Tribulations' elevates suffering to historical and apocalyptic significance unprecedented in human record.",
      "cross_refs": [
        {
          "work": "prayers-and-meditations",
          "para": 249,
          "snippet": "trials"
        },
        {
          "work": "gleanings",
          "para": 660,
          "snippet": "afflictions"
        },
        {
          "work": "prayers-and-meditations",
          "para": 63,
          "snippet": "the lands"
        },
        {
          "work": "kitab-i-iqan",
          "para": 28,
          "snippet": "afflicted"
        },
        {
          "work": "gleanings",
          "para": 640,
          "snippet": "subjected"
        },
        {
          "work": "kitab-i-iqan",
          "para": 145,
          "snippet": "sick"
        },
        {
          "work": "kitab-i-iqan",
          "para": 92,
          "snippet": "Yea"
        },
        {
          "work": "gleanings",
          "para": 410,
          "snippet": "affliction"
        }
      ]
    },
    {
      "term": "قبول",
      "transliteration": "q-b-l",
      "literal": "group; company; tribe; sort; kind",
      "se_rendering": "reconcile themselves",
      "note": "Usually 'company' or 'acceptance' (58 occ). 'Reconcile themselves' conveys willing submission to trial—pivotal psychological state absent in nominal definition.",
      "cross_refs": [
        {
          "work": "gleanings",
          "para": 698,
          "snippet": "company"
        },
        {
          "work": "prayers-and-meditations",
          "para": 552,
          "snippet": "seal of acceptance"
        },
        {
          "work": "gleanings",
          "para": 603,
          "snippet": "if it be accepted and take effect"
        },
        {
          "work": "kitab-i-iqan",
          "para": 146,
          "snippet": "breeze that bloweth from the meads of the good-pleasure of God"
        },
        {
          "work": "kitab-i-iqan",
          "para": 74,
          "snippet": "tribes"
        },
        {
          "work": "will-and-testament",
          "para": 24,
          "snippet": "kindreds and religions"
        },
        {
          "work": "gleanings",
          "para": 235,
          "snippet": "have come"
        },
        {
          "work": "gleanings",
          "para": 267,
          "snippet": "acknowledged"
        }
      ]
    },
    {
      "term": "منع",
      "transliteration": "m-n-ʿ",
      "literal": "forbidden; prevented; deprived",
      "se_rendering": "ban",
      "note": "Typically 'forbidden' or 'deprived' (36 occ). 'Ban' emphasizes authoritative divine restraint on worldly action—a protective decree rather than mere prohibition.",
      "cross_refs": [
        {
          "work": "will-and-testament",
          "para": 8,
          "snippet": "forbidden"
        },
        {
          "work": "gleanings",
          "para": 641,
          "snippet": "deprived"
        },
        {
          "work": "gleanings",
          "para": 181,
          "snippet": "be not deprived"
        },
        {
          "work": "will-and-testament",
          "para": 56,
          "snippet": "hindrance"
        },
        {
          "work": "prayers-and-meditations",
          "para": 674,
          "snippet": "which have hindered me"
        },
        {
          "work": "prayers-and-meditations",
          "para": 628,
          "snippet": "have failed to deter"
        },
        {
          "work": "prayers-and-meditations",
          "para": 74,
          "snippet": "withhold"
        },
        {
          "work": "gleanings",
          "para": 314,
          "snippet": "refused to allow"
        }
      ]
    },
    {
      "term": "اعلی",
      "transliteration": "ʿ-l-w",
      "literal": "highest; most high; supreme",
      "se_rendering": "the Pen of Glory",
      "note": "Standard 'the Most High' or 'the Most Sublime Pen' (74 occ). 'Pen of Glory' is unique here, uniting supreme authority with eschatological radiance.",
      "cross_refs": [
        {
          "work": "kitab-i-iqan",
          "para": 1,
          "snippet": "the Most High"
        },
        {
          "work": "gleanings",
          "para": 232,
          "snippet": "supreme"
        },
        {
          "work": "gleanings",
          "para": 616,
          "snippet": "the realms above"
        },
        {
          "work": "prayers-and-meditations",
          "para": 390,
          "snippet": "the Most Exalted, the Most High"
        },
        {
          "work": "gleanings",
          "para": 393,
          "snippet": "The Pen of the Most High"
        },
        {
          "work": "gleanings",
          "para": 697,
          "snippet": "the Dayspring of Glory"
        },
        {
          "work": "kitab-i-ahd",
          "para": 1,
          "snippet": "the Realm of Glory"
        },
        {
          "work": "kitab-i-iqan",
          "para": 257,
          "snippet": "the Báb, the Lord, the most exalted"
        }
      ]
    }
  ],
  "section_index": "122",
  "section": "122",
  "section_para": 1
}
