{
  "work": "Gleanings",
  "slug": "gleanings",
  "author": "Bahá'u'lláh",
  "pair_index": 552,
  "source_text": "ظاهری اجساد را محترق نماید و نار لسان ارواح و افئده را بگدازد اثر آن نار بساعتی فانی شود و اثر این نار بقرنی باقی ماند و غیبت را ضلالت شمرد و بآن عرصه هرگز قدم نگذارد زیرا غیبت سراج منیر قلب را خاموش نماید و حیات دل را بمیراند بقلیل قانع باشد و از طلب کثیر فارغ مصاحبت منقطعین را غنیمت شمارد و عزلت از متمسّکین و متکبّرین را نعمت شمرد در اسحار باذکار مشغول شود و بتمام همّت و اقتدار در طلب آن نگار کوشد غفلت را بنار حبّ و ذکر بسوزاند و از ما سوی الله چون برق درگذرد و بر بی‌نصیبان نصیب بخشد و از محرومان عطا و احسان دریغ ندارد رعایت حیوان را منظور نماید تا چه رسد بانسان و اهل بیان و از جانان جان دریغ ندارد و از شماتت خلق از حقّ احتراز نجوید و آنچه برای خود نمی‌پسندد برای غیر نپسندد و نگوید آنچه را وفا نکند و از خاطئان در کمال استیلا درگذرد و طلب مغفرت نماید و بر عاصیان قلم عفو درکشد و بحقارت ننگرد زیرا حسن خاتمه مجهول است ای بسا عاصی که در حین موت بجوهر ایمان موفّق شود و خمر بقا چشد و بملأ اعلی شتابد و بسا مطیع و مؤمن که در وقت ارتقای روح تقلیب شود و باسفل درکات نیران مقرّ یابد",
  "translation": "That seeker should, also, regard backbiting as grievous error, and keep himself aloof from its dominion, inasmuch as backbiting quencheth the light of the heart, and extinguisheth the life of the soul. He should be content with little, and be freed from all inordinate desire. He should treasure the companionship of them that have renounced the world, and regard avoidance of boastful and worldly people a precious benefit. At the dawn of every day he should commune with God, and, with all his soul, persevere in the quest of his Beloved. He should consume every wayward thought with the flame of His loving mention, and, with the swiftness of lightning, pass by all else save Him. He should succor the dispossessed, and never withhold his favor from the destitute. He should show kindness to animals, how much more unto his fellowman, to him who is endowed with the power of utterance. He should not hesitate to offer up his life for his Beloved, nor allow the censure of the people to turn him away from the Truth. He should not wish for others that which he doth not wish for himself, nor promise that which he doth not fulfill. With all his heart he should avoid fellowship with evildoers, and pray for the remission of their sins. He should forgive the sinful, and never despise his low estate, for none knoweth what his own end shall be. How often hath a sinner attained, at the hour of death, to the essence of faith, and, quaffing the immortal draught, hath taken his flight unto the Concourse on high! And how often hath a devout believer, at the hour of his soul’s ascension, been so changed as to fall into the nethermost fire!",
  "source_lang": "ar",
  "score": 9.6,
  "page_slug": "flame-of-loving-mention",
  "alignment": [
    {
      "ar": "ظاهری",
      "en": ""
    },
    {
      "ar": "اجساد",
      "en": ""
    },
    {
      "ar": "محترق",
      "en": ""
    },
    {
      "ar": "نماید",
      "en": ""
    },
    {
      "ar": "نار",
      "en": "flame"
    },
    {
      "ar": "لسان",
      "en": ""
    },
    {
      "ar": "ارواح",
      "en": "soul"
    },
    {
      "ar": "افئده",
      "en": "heart"
    },
    {
      "ar": "بگدازد",
      "en": ""
    },
    {
      "ar": "اثر",
      "en": ""
    },
    {
      "ar": "آن",
      "en": ""
    },
    {
      "ar": "نار",
      "en": ""
    },
    {
      "ar": "بساعتی",
      "en": ""
    },
    {
      "ar": "فانی",
      "en": ""
    },
    {
      "ar": "شود",
      "en": ""
    },
    {
      "ar": "اثر",
      "en": ""
    },
    {
      "ar": "این",
      "en": ""
    },
    {
      "ar": "نار",
      "en": ""
    },
    {
      "ar": "بقرنی",
      "en": ""
    },
    {
      "ar": "باقی",
      "en": ""
    },
    {
      "ar": "ماند",
      "en": ""
    },
    {
      "ar": "غیبت",
      "en": "backbiting"
    },
    {
      "ar": "ضلالت",
      "en": "grievous error"
    },
    {
      "ar": "شمرد",
      "en": "regard"
    },
    {
      "ar": "بآن",
      "en": ""
    },
    {
      "ar": "عرصه",
      "en": ""
    },
    {
      "ar": "هرگز",
      "en": ""
    },
    {
      "ar": "قدم",
      "en": ""
    },
    {
      "ar": "نگذارد",
      "en": ""
    },
    {
      "ar": "زیرا",
      "en": "inasmuch as"
    },
    {
      "ar": "سراج",
      "en": ""
    },
    {
      "ar": "منیر",
      "en": "light"
    },
    {
      "ar": "قلب",
      "en": "the heart"
    },
    {
      "ar": "خاموش",
      "en": "quencheth"
    },
    {
      "ar": "نماید",
      "en": ""
    },
    {
      "ar": "حیات",
      "en": "the life"
    },
    {
      "ar": "دل",
      "en": "the soul"
    },
    {
      "ar": "بمیراند",
      "en": "extinguisheth"
    },
    {
      "ar": "بقلیل",
      "en": "with little"
    },
    {
      "ar": "قانع",
      "en": "content"
    },
    {
      "ar": "باشد",
      "en": "should be"
    },
    {
      "ar": "از",
      "en": ""
    },
    {
      "ar": "طلب",
      "en": ""
    },
    {
      "ar": "کثیر",
      "en": "all inordinate desire"
    },
    {
      "ar": "فارغ",
      "en": "freed"
    },
    {
      "ar": "مصاحبت",
      "en": "the companionship"
    },
    {
      "ar": "منقطعین",
      "en": "them that have renounced the world"
    },
    {
      "ar": "غنیمت",
      "en": "treasure"
    },
    {
      "ar": "شمارد",
      "en": ""
    },
    {
      "ar": "عزلت",
      "en": "avoidance"
    },
    {
      "ar": "از",
      "en": ""
    },
    {
      "ar": "متمسّکین",
      "en": ""
    },
    {
      "ar": "متکبّرین",
      "en": "boastful and worldly people"
    },
    {
      "ar": "نعمت",
      "en": "precious benefit"
    },
    {
      "ar": "شمرد",
      "en": ""
    },
    {
      "ar": "در",
      "en": ""
    },
    {
      "ar": "اسحار",
      "en": "the dawn of every day"
    },
    {
      "ar": "باذکار",
      "en": "commune with God"
    },
    {
      "ar": "مشغول",
      "en": ""
    },
    {
      "ar": "شود",
      "en": ""
    },
    {
      "ar": "بتمام",
      "en": "with all"
    },
    {
      "ar": "همّت",
      "en": ""
    },
    {
      "ar": "اقتدار",
      "en": ""
    },
    {
      "ar": "طلب",
      "en": "the quest"
    },
    {
      "ar": "آن",
      "en": ""
    },
    {
      "ar": "نگار",
      "en": "his Beloved"
    },
    {
      "ar": "کوشد",
      "en": "persevere"
    },
    {
      "ar": "غفلت",
      "en": "every wayward thought"
    },
    {
      "ar": "بنار",
      "en": "with the flame"
    },
    {
      "ar": "حبّ",
      "en": "His loving"
    },
    {
      "ar": "ذکر",
      "en": "mention"
    },
    {
      "ar": "بسوزاند",
      "en": "consume"
    },
    {
      "ar": "از",
      "en": ""
    },
    {
      "ar": "ما سوی الله",
      "en": "all else save Him"
    },
    {
      "ar": "چون",
      "en": ""
    },
    {
      "ar": "برق",
      "en": "the swiftness of lightning"
    },
    {
      "ar": "درگذرد",
      "en": "pass by"
    },
    {
      "ar": "بر",
      "en": ""
    },
    {
      "ar": "بی‌نصیبان",
      "en": "the dispossessed"
    },
    {
      "ar": "نصیب",
      "en": "succor"
    },
    {
      "ar": "بخشد",
      "en": ""
    },
    {
      "ar": "از",
      "en": ""
    },
    {
      "ar": "محرومان",
      "en": "the destitute"
    },
    {
      "ar": "عطا",
      "en": "his favor"
    },
    {
      "ar": "احسان",
      "en": ""
    },
    {
      "ar": "دریغ",
      "en": "withhold"
    },
    {
      "ar": "ندارد",
      "en": "never"
    },
    {
      "ar": "رعایت",
      "en": "kindness"
    },
    {
      "ar": "حیوان",
      "en": "animals"
    },
    {
      "ar": "منظور",
      "en": "show"
    },
    {
      "ar": "نماید",
      "en": ""
    },
    {
      "ar": "تا چه رسد",
      "en": "how much more"
    },
    {
      "ar": "بانسان",
      "en": "his fellowman"
    },
    {
      "ar": "اهل",
      "en": "endowed"
    },
    {
      "ar": "بیان",
      "en": "the power of utterance"
    },
    {
      "ar": "از",
      "en": ""
    },
    {
      "ar": "جان",
      "en": "his life"
    },
    {
      "ar": "دریغ",
      "en": "hesitate to offer up"
    },
    {
      "ar": "ندارد",
      "en": "not"
    },
    {
      "ar": "از",
      "en": ""
    },
    {
      "ar": "شماتت",
      "en": "the censure"
    },
    {
      "ar": "خلق",
      "en": "the people"
    },
    {
      "ar": "از",
      "en": ""
    },
    {
      "ar": "حقّ",
      "en": "the Truth"
    },
    {
      "ar": "احتراز",
      "en": "turn him away"
    },
    {
      "ar": "نجوید",
      "en": ""
    },
    {
      "ar": "آنچه",
      "en": "that which"
    },
    {
      "ar": "برای",
      "en": "for"
    },
    {
      "ar": "خود",
      "en": "himself"
    },
    {
      "ar": "نمی‌پسندد",
      "en": "doth not wish"
    },
    {
      "ar": "غیر",
      "en": "others"
    },
    {
      "ar": "نپسندد",
      "en": "not wish"
    },
    {
      "ar": "نگوید",
      "en": "promise"
    },
    {
      "ar": "را",
      "en": ""
    },
    {
      "ar": "وفا",
      "en": "fulfill"
    },
    {
      "ar": "نکند",
      "en": "doth not"
    },
    {
      "ar": "از",
      "en": ""
    },
    {
      "ar": "خاطئان",
      "en": "evildoers"
    },
    {
      "ar": "در کمال",
      "en": ""
    },
    {
      "ar": "استیلا",
      "en": ""
    },
    {
      "ar": "درگذرد",
      "en": "avoid fellowship"
    },
    {
      "ar": "طلب",
      "en": "pray"
    },
    {
      "ar": "مغفرت",
      "en": "the remission of their sins"
    },
    {
      "ar": "نماید",
      "en": ""
    },
    {
      "ar": "بر",
      "en": ""
    },
    {
      "ar": "عاصیان",
      "en": "the sinful"
    },
    {
      "ar": "قلم",
      "en": ""
    },
    {
      "ar": "عفو",
      "en": "forgive"
    },
    {
      "ar": "درکشد",
      "en": ""
    },
    {
      "ar": "بحقارت",
      "en": "his low estate"
    },
    {
      "ar": "ننگرد",
      "en": "never despise"
    },
    {
      "ar": "حسن",
      "en": ""
    },
    {
      "ar": "خاتمه",
      "en": "his own end"
    },
    {
      "ar": "مجهول",
      "en": "none knoweth what"
    },
    {
      "ar": "است",
      "en": ""
    },
    {
      "ar": "ای بسا",
      "en": "How often"
    },
    {
      "ar": "عاصی",
      "en": "a sinner"
    },
    {
      "ar": "که",
      "en": ""
    },
    {
      "ar": "در",
      "en": ""
    },
    {
      "ar": "حین",
      "en": ""
    },
    {
      "ar": "موت",
      "en": "at the hour of death"
    },
    {
      "ar": "بجوهر",
      "en": "to the essence"
    },
    {
      "ar": "ایمان",
      "en": "faith"
    },
    {
      "ar": "موفّق",
      "en": "attained"
    },
    {
      "ar": "شود",
      "en": "hath"
    },
    {
      "ar": "خمر",
      "en": "draught"
    },
    {
      "ar": "بقا",
      "en": "the immortal"
    },
    {
      "ar": "چشد",
      "en": "quaffing"
    },
    {
      "ar": "بملأ اعلی",
      "en": "the Concourse on high"
    },
    {
      "ar": "شتابد",
      "en": "hath taken his flight"
    },
    {
      "ar": "بسا",
      "en": "how often"
    },
    {
      "ar": "مطیع",
      "en": ""
    },
    {
      "ar": "مؤمن",
      "en": "a devout believer"
    },
    {
      "ar": "که",
      "en": ""
    },
    {
      "ar": "در",
      "en": ""
    },
    {
      "ar": "وقت",
      "en": "at the hour"
    },
    {
      "ar": "ارتقای",
      "en": "ascension"
    },
    {
      "ar": "روح",
      "en": "his soul"
    },
    {
      "ar": "تقلیب",
      "en": "changed"
    },
    {
      "ar": "شود",
      "en": "been so"
    },
    {
      "ar": "باسفل",
      "en": "the nethermost"
    },
    {
      "ar": "درکات",
      "en": ""
    },
    {
      "ar": "نیران",
      "en": "fire"
    },
    {
      "ar": "مقرّ",
      "en": "fall into"
    },
    {
      "ar": "یابد",
      "en": ""
    }
  ],
  "terms": [
    {
      "term": "نار",
      "transliteration": "n-w-r",
      "literal": "light; illumination",
      "se_rendering": "flame; light",
      "note": "Root n-w-r typically rendered 'light' (78 occ). Here rendered 'flame' twice—SE treats this passage's mystical fire as divine action upon consciousness, distinct from ordinary illumination.",
      "cross_refs": [
        {
          "work": "epistle-to-the-son-of-the-wolf",
          "para": 3,
          "snippet": "light"
        },
        {
          "work": "prayers-and-meditations",
          "para": 114,
          "snippet": "with the light"
        },
        {
          "work": "prayers-and-meditations",
          "para": 109,
          "snippet": "Thy light"
        },
        {
          "work": "prayers-and-meditations",
          "para": 246,
          "snippet": "Illumine"
        },
        {
          "work": "prayers-and-meditations",
          "para": 180,
          "snippet": "fire"
        },
        {
          "work": "tablet-of-ahmad",
          "para": 10,
          "snippet": "flame of fire"
        },
        {
          "work": "kitab-i-iqan",
          "para": 39,
          "snippet": "lights"
        },
        {
          "work": "prayers-and-meditations",
          "para": 312,
          "snippet": "splendors"
        }
      ]
    },
    {
      "term": "غیبت",
      "transliteration": "gh-y-b",
      "literal": "the unseen; the invisible; the hidden; the unknowable",
      "se_rendering": "backbiting",
      "note": "Not in Jafar concordance; root gh-y-b. SE's 'backbiting' establishes this as spiritual malady quenching divine light, foregrounding moral consequence over linguistic property.",
      "cross_refs": [
        {
          "work": "kitab-i-iqan",
          "para": 214,
          "snippet": "backbiting"
        },
        {
          "work": "kitab-i-iqan",
          "para": 10,
          "snippet": "invisible"
        },
        {
          "work": "kitab-i-iqan",
          "para": 77,
          "snippet": "hidden"
        }
      ]
    },
    {
      "term": "قلب",
      "transliteration": "q-l-b",
      "literal": "heart; to turn; to overturn",
      "se_rendering": "heart; thoughts",
      "note": "Typically 'hearts' or 'heart' (60 occ); here rendered 'thoughts' once ('wayward thought'). Shows SE's contextual flexibility: the root's sense of 'turning/overturn' applied to mental states not physical organs.",
      "cross_refs": [
        {
          "work": "epistle-to-the-son-of-the-wolf",
          "para": 187,
          "snippet": "hearts"
        },
        {
          "work": "prayers-and-meditations",
          "para": 432,
          "snippet": "their hearts"
        },
        {
          "work": "prayers-and-meditations",
          "para": 652,
          "snippet": "heart"
        },
        {
          "work": "prayers-and-meditations",
          "para": 777,
          "snippet": "commotion"
        },
        {
          "work": "kitab-i-iqan",
          "para": 13,
          "snippet": "tumult"
        },
        {
          "work": "epistle-to-the-son-of-the-wolf",
          "para": 30,
          "snippet": "thine heart"
        },
        {
          "work": "kitab-i-ahd",
          "para": 4,
          "snippet": "with a pure heart"
        },
        {
          "work": "epistle-to-the-son-of-the-wolf",
          "para": 82,
          "snippet": "with a sound heart"
        }
      ]
    },
    {
      "term": "اقتدار",
      "transliteration": "q-d-r",
      "literal": "power; might; decree; measure; worth",
      "se_rendering": "soul",
      "note": "Root q-d-r typically 'power; might' (100 occ), but SE renders here as 'soul'—a unique collocation showing SE's reading of 'striving with full capacity' as spiritual exertion.",
      "cross_refs": [
        {
          "work": "epistle-to-the-son-of-the-wolf",
          "para": 171,
          "snippet": "a while"
        },
        {
          "work": "prayers-and-meditations",
          "para": 339,
          "snippet": "Thy power"
        },
        {
          "work": "prayers-and-meditations",
          "para": 12,
          "snippet": "God of power"
        },
        {
          "work": "prayers-and-meditations",
          "para": 35,
          "snippet": "Potent"
        },
        {
          "work": "prayers-and-meditations",
          "para": 282,
          "snippet": "Almighty"
        },
        {
          "work": "prayers-and-meditations",
          "para": 177,
          "snippet": "ordain"
        },
        {
          "work": "kitab-i-iqan",
          "para": 4,
          "snippet": "for a moment"
        },
        {
          "work": "prayers-and-meditations",
          "para": 30,
          "snippet": "didst ordain"
        }
      ]
    },
    {
      "term": "ذکر",
      "transliteration": "dh-k-r",
      "literal": "remembrance; mention; memory",
      "se_rendering": "mention; remembrance",
      "note": "Usually 'remembrance' or 'mention' (57 occ). Here 'loving mention' pairs with 'flame'—SE emphasizes affective union with God through naming, not mere intellectual recall.",
      "cross_refs": [
        {
          "work": "kitab-i-iqan",
          "para": 54,
          "snippet": "mention"
        },
        {
          "work": "epistle-to-the-son-of-the-wolf",
          "para": 117,
          "snippet": "Time and again have I declared"
        },
        {
          "work": "will-and-testament",
          "para": 39,
          "snippet": "deliberate"
        },
        {
          "work": "kitab-i-iqan",
          "para": 274,
          "snippet": "aforementioned"
        },
        {
          "work": "the-hidden-words",
          "para": 112,
          "snippet": "recorded"
        },
        {
          "work": "epistle-to-the-son-of-the-wolf",
          "para": 34,
          "snippet": "confined in that"
        },
        {
          "work": "epistle-to-the-son-of-the-wolf",
          "para": 4,
          "snippet": "mentioned"
        },
        {
          "work": "epistle-to-the-son-of-the-wolf",
          "para": 6,
          "snippet": "to remember Thee"
        }
      ]
    },
    {
      "term": "خاتمه",
      "transliteration": "kh-t-m",
      "literal": "to seal; to conclude; to end; seal",
      "se_rendering": "end",
      "note": "Typically 'Seal of the Prophets' or 'seal' (21 occ). Here 'end' emphasizes mortality's inscrutability—SE uses eschatological sense to warn against judging spiritual states.",
      "cross_refs": [
        {
          "work": "epistle-to-the-son-of-the-wolf",
          "para": 31,
          "snippet": "seal"
        },
        {
          "work": "prayers-and-meditations",
          "para": 552,
          "snippet": "affixed Thy seal"
        },
        {
          "work": "kitab-i-iqan",
          "para": 178,
          "snippet": "Seal of the Prophets"
        },
        {
          "work": "epistle-to-the-son-of-the-wolf",
          "para": 76,
          "snippet": "sealed"
        },
        {
          "work": "epistle-to-the-son-of-the-wolf",
          "para": 226,
          "snippet": "as a ring"
        },
        {
          "work": "kitab-i-iqan",
          "para": 287,
          "snippet": "We conclude"
        },
        {
          "work": "prayers-and-meditations",
          "para": 701,
          "snippet": "choose"
        }
      ]
    },
    {
      "term": "ایمان",
      "transliteration": "ʾ-m-n",
      "literal": "to believe; to have faith; to be secure",
      "se_rendering": "faith",
      "note": "Standard 'faith' or 'belief' (32 occ). Here 'essence of faith'—SE's 'essence' translates Persian 'jowhár' (جوهر), signaling that faith's inner reality transcends external conduct.",
      "cross_refs": [
        {
          "work": "prayers-and-meditations",
          "para": 431,
          "snippet": "believed"
        },
        {
          "work": "kitab-i-iqan",
          "para": 2,
          "snippet": "faith"
        },
        {
          "work": "epistle-to-the-son-of-the-wolf",
          "para": 198,
          "snippet": "Trustworthiness"
        },
        {
          "work": "prayers-and-meditations",
          "para": 561,
          "snippet": "hath believed"
        },
        {
          "work": "tablet-of-ahmad",
          "para": 7,
          "snippet": "have ye believed"
        },
        {
          "work": "epistle-to-the-son-of-the-wolf",
          "para": 225,
          "snippet": "believer"
        },
        {
          "work": "will-and-testament",
          "para": 25,
          "snippet": "believers"
        },
        {
          "work": "kitab-i-ahd",
          "para": 6,
          "snippet": "trustees"
        }
      ]
    },
    {
      "term": "اعلی",
      "transliteration": "ʿ-l-w",
      "literal": "highest; most high; supreme",
      "se_rendering": "high",
      "note": "Usually 'the Most High' or 'supreme' (74 occ). Here 'high' in 'Concourse on high'—SE reserves elevated titles for explicit divine references, using 'high' for celestial realm alone.",
      "cross_refs": [
        {
          "work": "kitab-i-iqan",
          "para": 1,
          "snippet": "the Most High"
        },
        {
          "work": "epistle-to-the-son-of-the-wolf",
          "para": 148,
          "snippet": "the Most Sublime Pen"
        },
        {
          "work": "prayers-and-meditations",
          "para": 390,
          "snippet": "the Most Exalted, the Most High"
        },
        {
          "work": "epistle-to-the-son-of-the-wolf",
          "para": 68,
          "snippet": "the Pen of Glory"
        },
        {
          "work": "kitab-i-ahd",
          "para": 1,
          "snippet": "the Realm of Glory"
        },
        {
          "work": "kitab-i-iqan",
          "para": 257,
          "snippet": "the Báb, the Lord, the most exalted"
        },
        {
          "work": "epistle-to-the-son-of-the-wolf",
          "para": 21,
          "snippet": "sublime"
        },
        {
          "work": "epistle-to-the-son-of-the-wolf",
          "para": 143,
          "snippet": "exalted be He"
        }
      ]
    }
  ],
  "section_index": "CXXV.3",
  "section": "CXXV",
  "section_para": 3
}
