{
  "work": "Kitab-i-Iqan",
  "slug": "kitab-i-iqan",
  "author": "Bahá'u'lláh",
  "pair_index": 191,
  "source_text": "از قبل دو مقام از برای شموس مشرقه از مشارق الهيّه بيان نموديم.  يکی مقام توحيد و رتبه تفريد، چنانچه از قبل ذکر شد :  \"لا نُفَرِّقُ بَينَ اَحَدٍ مِنهُم.\"  و مقام ديگر مقام تفصيل و عالم خلق و رتبه حدودات بشريّه است.  در اين مقام  هر کدام را هيکلی معيّن و امری مقرّر و ظهوری مقدّر وحدودی مخصوص است چنانچه هر کدام به اسمی موسوم و به وصفی موصوف و به امری بديع و شرعی جديد مأمورند. چنانچه می فرمايد:  \"تِلْکَ الرُّسُلُ فَضَّلْنَا بَعْضَهُم عَلَی بَعضٍ مِنهُمْ مَنْ کَلَّمَ اللّهُ و رَفَعَ بَعْضَهُمْ دَرَجَاتٍ و آتَيْنَا عِيسَی ابْنَ مَرْيَمَ البيِّنَاتِ و اَيَّدْنَاهُ بِرُوحِ القُدُسِ.\"",
  "translation": "We have already in the foregoing pages assigned two stations unto each of the Luminaries arising from the Daysprings of eternal holiness. One of these stations, the station of essential unity, We have already explained. “No distinction do We make between any of them.” The other is the station of distinction, and pertaineth to the world of creation and to the limitations thereof. In this respect, each Manifestation of God hath a distinct individuality, a definitely prescribed mission, a predestined Revelation, and specially designated limitations. Each one of them is known by a different name, is characterized by a special attribute, fulfils a definite Mission, and is entrusted with a particular Revelation. Even as He saith: “Some of the Apostles We have caused to excel the others. To some God hath spoken, some He hath raised and exalted. And to Jesus, Son of Mary, We gave manifest signs, and We strengthened Him with the Holy Spirit.”",
  "source_lang": "fa",
  "score": 10,
  "page_slug": "station-essential-unity-distinction",
  "alignment": [
    {
      "ar": "از قبل",
      "en": "already in the foregoing pages"
    },
    {
      "ar": "دو",
      "en": "two"
    },
    {
      "ar": "مقام",
      "en": "stations"
    },
    {
      "ar": "شموس",
      "en": "Luminaries"
    },
    {
      "ar": "مشرقه",
      "en": "arising"
    },
    {
      "ar": "مشارق",
      "en": "Daysprings"
    },
    {
      "ar": "الهيّه",
      "en": "eternal holiness"
    },
    {
      "ar": "بيان نموديم",
      "en": "assigned"
    },
    {
      "ar": "يکی",
      "en": "One"
    },
    {
      "ar": "مقام",
      "en": "station"
    },
    {
      "ar": "توحيد",
      "en": "essential unity"
    },
    {
      "ar": "چنانچه",
      "en": "Even as"
    },
    {
      "ar": "ذکر شد",
      "en": "explained"
    },
    {
      "ar": "مقام ديگر",
      "en": "The other is the station"
    },
    {
      "ar": "تفصيل",
      "en": "distinction"
    },
    {
      "ar": "عالم",
      "en": "world"
    },
    {
      "ar": "خلق",
      "en": "creation"
    },
    {
      "ar": "حدودات",
      "en": "limitations"
    },
    {
      "ar": "بشريّه",
      "en": "limitations thereof"
    },
    {
      "ar": "در اين مقام",
      "en": "In this respect"
    },
    {
      "ar": "هر کدام",
      "en": "each"
    },
    {
      "ar": "هيکلی",
      "en": "individuality"
    },
    {
      "ar": "معيّن",
      "en": "distinct"
    },
    {
      "ar": "امری",
      "en": "Mission"
    },
    {
      "ar": "مقرّر",
      "en": "prescribed"
    },
    {
      "ar": "ظهوری",
      "en": "Revelation"
    },
    {
      "ar": "مقدّر",
      "en": "predestined"
    },
    {
      "ar": "مخصوص",
      "en": "specially designated"
    },
    {
      "ar": "هر کدام",
      "en": "Each one"
    },
    {
      "ar": "اسمی",
      "en": "name"
    },
    {
      "ar": "موسوم",
      "en": "known"
    },
    {
      "ar": "وصفی",
      "en": "attribute"
    },
    {
      "ar": "موصوف",
      "en": "characterized"
    },
    {
      "ar": "امری بديع",
      "en": "definite Mission"
    },
    {
      "ar": "جديد",
      "en": "particular"
    },
    {
      "ar": "مأمورند",
      "en": "entrusted"
    },
    {
      "ar": "می فرمايد",
      "en": "He saith"
    },
    {
      "ar": "رَفَعَ بَعْضَهُمْ دَرَجَاتٍ",
      "en": "some He hath raised and exalted"
    }
  ],
  "terms": [
    {
      "term": "مقام",
      "transliteration": "q-w-m",
      "literal": "rising; standing; uprising; resurrection",
      "se_rendering": "station",
      "note": "Root q-w-m usually yields 'Resurrection' or 'arise' across 109 occurrences. Here rendered 'station'—a metaphysical rather than temporal sense, indicating a state of being rather than an event.",
      "cross_refs": [
        {
          "work": "gleanings",
          "para": 437,
          "snippet": "arise"
        },
        {
          "work": "gleanings",
          "para": 513,
          "snippet": "dedicateth"
        },
        {
          "work": "epistle-to-the-son-of-the-wolf",
          "para": 74,
          "snippet": "rise"
        },
        {
          "work": "will-and-testament",
          "para": 8,
          "snippet": "peoples"
        },
        {
          "work": "gleanings",
          "para": 693,
          "snippet": "commandments"
        },
        {
          "work": "gleanings",
          "para": 628,
          "snippet": "My commandments"
        },
        {
          "work": "gleanings",
          "para": 518,
          "snippet": "steadfast"
        },
        {
          "work": "prayers-and-meditations",
          "para": 38,
          "snippet": "steadfast in faith"
        }
      ]
    },
    {
      "term": "تفصيل",
      "transliteration": "f-s-l",
      "literal": "detail; distinction; differentiation; to detail; to separate",
      "se_rendering": "distinction",
      "note": "Root f-s-l typically 'distinction and separation' or 'severed' (18 occ.). Here 'distinction' alone—SE isolates the term's positive, differentiating sense rather than emphasizing severance.",
      "cross_refs": [
        {
          "work": "will-and-testament",
          "para": 11,
          "snippet": "hath been severed"
        },
        {
          "work": "gleanings",
          "para": 129,
          "snippet": "distinction and separation"
        },
        {
          "work": "prayers-and-meditations",
          "para": 615,
          "snippet": "divided between"
        },
        {
          "work": "gleanings",
          "para": 356,
          "snippet": "we have expounded"
        },
        {
          "work": "prayers-and-meditations",
          "para": 73,
          "snippet": "discriminating Word"
        },
        {
          "work": "gleanings",
          "para": 101,
          "snippet": "station of distinction"
        },
        {
          "work": "gleanings",
          "para": 345,
          "snippet": "detail"
        },
        {
          "work": "prayers-and-meditations",
          "para": 227,
          "snippet": "distinguished"
        }
      ]
    },
    {
      "term": "هيکلی",
      "transliteration": "h-k-l",
      "literal": "temple; structure; form; body",
      "se_rendering": "individuality",
      "note": "Usually 'Temple' or 'Súratu'l-Haykal' (20 occ.). 'Individuality' here—SE renders the Manifestation's bodily/formal nature as distinctness of character, not literal structure.",
      "cross_refs": [
        {
          "work": "will-and-testament",
          "para": 1,
          "snippet": "Temple"
        },
        {
          "work": "epistle-to-the-son-of-the-wolf",
          "para": 96,
          "snippet": "Súratu'l-Haykal"
        },
        {
          "work": "gleanings",
          "para": 168,
          "snippet": "beauty of the immortal Being"
        },
        {
          "work": "the-hidden-words",
          "para": 154,
          "snippet": "Being"
        },
        {
          "work": "gleanings",
          "para": 326,
          "snippet": "human temple"
        },
        {
          "work": "epistle-to-the-son-of-the-wolf",
          "para": 28,
          "snippet": "body"
        },
        {
          "work": "gleanings",
          "para": 359,
          "snippet": "person"
        },
        {
          "work": "epistle-to-the-son-of-the-wolf",
          "para": 196,
          "snippet": "temples"
        }
      ]
    },
    {
      "term": "امری",
      "transliteration": "ʾ-m-r",
      "literal": "command; cause; matter; affair",
      "se_rendering": "Mission",
      "note": "Usually 'Cause' or 'Revelation' (75 occ.). Rendered 'Mission' here and 'Revelation' elsewhere in the same passage—SE varies the rendering within a single paragraph, likely tracking the referents' different contexts.",
      "cross_refs": [
        {
          "work": "will-and-testament",
          "para": 1,
          "snippet": "His Cause"
        },
        {
          "work": "gleanings",
          "para": 586,
          "snippet": "His command"
        },
        {
          "work": "gleanings",
          "para": 691,
          "snippet": "His Revelation"
        },
        {
          "work": "gleanings",
          "para": 723,
          "snippet": "Cause"
        },
        {
          "work": "prayers-and-meditations",
          "para": 797,
          "snippet": "Thy Cause"
        },
        {
          "work": "gleanings",
          "para": 8,
          "snippet": "Revelation"
        },
        {
          "work": "prayers-and-meditations",
          "para": 597,
          "snippet": "service"
        },
        {
          "work": "epistle-to-the-son-of-the-wolf",
          "para": 167,
          "snippet": "things"
        }
      ]
    },
    {
      "term": "بديع",
      "transliteration": "b-d-ʿ",
      "literal": "to create; most wondrous; excel",
      "se_rendering": "definite",
      "note": "Typically 'most wondrous' or 'creation' (21 occ.). Here 'definite'—a rare choice suggesting the divine creativity's purposefulness rather than its wondrousness, embedded in the phrase 'definite Mission.'",
      "cross_refs": [
        {
          "work": "will-and-testament",
          "para": 2,
          "snippet": "most wondrous"
        },
        {
          "work": "the-hidden-words",
          "para": 65,
          "snippet": "creation"
        },
        {
          "work": "will-and-testament",
          "para": 6,
          "snippet": "Badí'u'lláh"
        },
        {
          "work": "epistle-to-the-son-of-the-wolf",
          "para": 191,
          "snippet": "the eye of the universe"
        },
        {
          "work": "gleanings",
          "para": 205,
          "snippet": "wondrous"
        },
        {
          "work": "kitab-i-ahd",
          "para": 4,
          "snippet": "Mighty, the Wondrous"
        },
        {
          "work": "prayers-and-meditations",
          "para": 315,
          "snippet": "kingdoms of creation"
        },
        {
          "work": "epistle-to-the-son-of-the-wolf",
          "para": 202,
          "snippet": "new"
        }
      ]
    },
    {
      "term": "بروح",
      "transliteration": "r-w-h",
      "literal": "to go; to depart; to rest; spirit; soul",
      "se_rendering": "Spirit",
      "note": "Typically 'spirit' or 'the Spirit' (34 occ.). 'Holy Spirit' (added article 'Holy' from the source Qur'anic verse)—SE preserves the sacred epithet when quoting scripture, marking textual hierarchy.",
      "cross_refs": [
        {
          "work": "gleanings",
          "para": 164,
          "snippet": "My Well-Beloved"
        },
        {
          "work": "gleanings",
          "para": 246,
          "snippet": "My"
        },
        {
          "work": "gleanings",
          "para": 367,
          "snippet": "spirit"
        },
        {
          "work": "prayers-and-meditations",
          "para": 702,
          "snippet": "my spirit"
        },
        {
          "work": "gleanings",
          "para": 548,
          "snippet": "spiritual"
        },
        {
          "work": "the-hidden-words",
          "para": 20,
          "snippet": "a breath of My own Spirit"
        },
        {
          "work": "gleanings",
          "para": 337,
          "snippet": "human souls"
        },
        {
          "work": "gleanings",
          "para": 50,
          "snippet": "the splendors"
        }
      ]
    }
  ],
  "section_index": "191",
  "section": "191",
  "section_para": 1
}
