{
  "work": "Kitab-i-Iqan",
  "slug": "kitab-i-iqan",
  "author": "Bahá'u'lláh",
  "pair_index": 96,
  "source_text": "چنانچه اليوم مشاهده می شود که چه مقدار ردّ بر اين امر بديع، علمای جاهل عصر نوشتهاند و گمان نمودهاند که اين مفتريّات مطابق آيات کتاب و موافق کلمات اولی الالباب است.",
  "translation": "The same may be witnessed today. Consider how abundant are the denunciations written by the foolish divines of this age against this most wondrous Cause! How vain their imaginings that these calumnies are in conformity with the verses of God’s sacred Book, and in consonance with the utterances of men of discernment!",
  "source_lang": "fa",
  "score": 10,
  "page_slug": "calumnies-wondrous-cause",
  "alignment": [
    {
      "ar": "چنانچه",
      "en": "The same"
    },
    {
      "ar": "اليوم",
      "en": "today"
    },
    {
      "ar": "مشاهده می شود",
      "en": "may be witnessed"
    },
    {
      "ar": "چه مقدار",
      "en": "how abundant"
    },
    {
      "ar": "ردّ",
      "en": "denunciations"
    },
    {
      "ar": "بر",
      "en": "against"
    },
    {
      "ar": "اين",
      "en": "this"
    },
    {
      "ar": "امر",
      "en": "Cause"
    },
    {
      "ar": "بديع",
      "en": "most wondrous"
    },
    {
      "ar": "علمای",
      "en": "divines"
    },
    {
      "ar": "جاهل",
      "en": "foolish"
    },
    {
      "ar": "عصر",
      "en": "this age"
    },
    {
      "ar": "نوشتهاند",
      "en": "written"
    },
    {
      "ar": "گمان نمودهاند",
      "en": "their imaginings"
    },
    {
      "ar": "اين",
      "en": "these"
    },
    {
      "ar": "مفتريّات",
      "en": "calumnies"
    },
    {
      "ar": "مطابق",
      "en": "in conformity with"
    },
    {
      "ar": "آيات",
      "en": "verses"
    },
    {
      "ar": "موافق",
      "en": "in consonance with"
    },
    {
      "ar": "کلمات",
      "en": "utterances"
    },
    {
      "ar": "اولی الالباب",
      "en": "men of discernment"
    }
  ],
  "terms": [
    {
      "term": "مشاهده",
      "transliteration": "sh-h-d",
      "literal": "witnessed; observed; seen; evident; manifest",
      "se_rendering": "The same may be witnessed today",
      "note": "",
      "cross_refs": [
        {
          "work": "gleanings",
          "para": 607,
          "snippet": "manifest"
        },
        {
          "work": "prayers-and-meditations",
          "para": 811,
          "snippet": "I bear witness"
        },
        {
          "work": "epistle-to-the-son-of-the-wolf",
          "para": 6,
          "snippet": "I testify"
        },
        {
          "work": "gleanings",
          "para": 298,
          "snippet": "witness"
        },
        {
          "work": "epistle-to-the-son-of-the-wolf",
          "para": 253,
          "snippet": "martyrdom"
        },
        {
          "work": "gleanings",
          "para": 134,
          "snippet": "God witnesseth"
        },
        {
          "work": "prayers-and-meditations",
          "para": 230,
          "snippet": "God testifieth"
        },
        {
          "work": "tablet-of-the-holy-mariner",
          "para": 57,
          "snippet": "beheld"
        }
      ]
    },
    {
      "term": "مفتریّات",
      "transliteration": "f-t-r-y",
      "literal": "slander; calumny; fabrications; false accusations",
      "se_rendering": "calumnies",
      "note": "Consistent 'calumnies' (7 occ). Core negative vocabulary for SE's polemic against clerical opposition.",
      "cross_refs": [
        {
          "work": "epistle-to-the-son-of-the-wolf",
          "para": 140,
          "snippet": "calumnies"
        },
        {
          "work": "fire-tablet",
          "para": 30,
          "snippet": "slander"
        },
        {
          "work": "will-and-testament",
          "para": 34,
          "snippet": "hurled their calumny"
        }
      ]
    }
  ],
  "section_index": "96",
  "section": "96",
  "section_para": 1
}
